{
    "info" : {
        "generated_by" : "MachLine (c) 2023 USU Aerolab",
        "executed" : "Thu Oct 19 23:35:32 2023"
    },
    "mesh_info" : {
        "N_body_panels" : 7904,
        "N_body_vertices" : 4070,
        "N_wake_panels" : 232,
        "N_wake_filaments" : 0,
        "average_characteristic_length" : 1.50607415253950E-001,
        "max_flow_turning_angle" : 1.72084793158967E+002
    },
    "solver_results" : {
        "solver_status_code" : 0,
        "system_dimension" : 4070,
        "timing" : {
            "system_sorting" : 2.81716000000000E-002,
            "preconditioner" : 4.20903000000000E-002,
            "matrix_solver" : 8.41995000000000E+000
        },
        "iterations" : 572,
        "system_lower_bandwidth" : 274,
        "residual" : {
            "max" : 2.46759210287273E-013,
            "norm" : 7.60639237866442E-013
        }
    },
    "pressure_calculations" : {
        "isentropic_rule" : {
            "max" : 1.13509452054209E+000,
            "min" : -4.83942899277379E-001
        }
    },
    "total_forces" : {
        "Cx" : 6.47701282442857E-002,
        "Cy" : 1.00772473465602E-007,
        "Cz" : 2.22919881770956E-001
    },
    "total_moments" : {
        "CMx" : 1.12703045360534E-002,
        "CMy" : -4.60532083129642E+001,
        "CMz" : 1.74371085438906E-004
    },
    "input" : {
        "flow" : {
            "freestream_velocity" : [
                    9.96194698091746E-001,
                    0.00000000000000E+000,
                    8.71557427476582E-002
                ],
            "freestream_mach_number" : 1.70000000000000E+000
        },
        "geometry" : {
            "file" : "studies/filament_studies/Grid_convergence/meshes/bi_plane_grid_convergence_9.stl",
            "spanwise_axis" : "+y",
            "reference" : {
                "area" : 5.00000000000000E+001
            },
            "wake_model" : {
                "wake_present" : true,
                "append_wake" : true,
                "trefftz_distance" : 60,
                "wake_type" : "panels"
            }
        },
        "solver" : {
            "ormulation" : "neumann-mass-flux",
            "formulation" : "dirichlet-morino",
            "matrix_solver" : "GMRES",
            "write_A_and_b" : false
        },
        "post_processing" : {
            "pressure_rules" : {
                "ncompressible" : true
            }
        },
        "output" : {
            "body_file" : "studies/filament_studies/Grid_convergence/results/9.vtk",
            "wake_file" : "studies/filament_studies/Grid_convergence/results/9_wake.vtk",
            "report_file" : "studies/filament_studies/Grid_convergence/reports/9.json"
        }
    },
    "total_runtime" : 1.32030000000000E+001
}
