{
    "info" : {
        "generated_by" : "MachLine (c) 2023 USU Aerolab",
        "executed" : "Wed Nov 29 13:22:32 2023"
    },
    "mesh_info" : {
        "N_body_panels" : 24416,
        "N_body_vertices" : 12430,
        "N_wake_panels" : 440,
        "N_wake_filaments" : 0,
        "average_characteristic_length" : 5.27231145966501E-002,
        "max_flow_turning_angle" : 1.64325276100513E+002
    },
    "solver_results" : {
        "solver_status_code" : 0,
        "system_dimension" : 12430,
        "timing" : {
            "system_sorting" : 3.94000000000000E-005,
            "preconditioner" : 4.65126500000000E-001,
            "matrix_solver" : 1.43117778100000E+002
        },
        "iterations" : 999,
        "residual" : {
            "max" : 7.95578880552483E-013,
            "norm" : 5.70634111830413E-012
        }
    },
    "pressure_calculations" : {
        "incompressible_rule" : {
            "max" : 8.83528651756232E-001,
            "min" : -4.91792625736068E+000
        }
    },
    "total_forces" : {
        "Cx" : -3.10524880648414E-002,
        "Cy" : -7.15317481438960E-006,
        "Cz" : 5.73109505684706E-001
    },
    "total_moments" : {
        "CMx" : -1.04251678775178E-001,
        "CMy" : -1.07471475682303E+002,
        "CMz" : 3.69807731324414E-003
    },
    "input" : {
        "flow" : {
            "freestream_velocity" : [
                    9.96194698091746E-001,
                    0.00000000000000E+000,
                    8.71557427476582E-002
                ],
            "freestream_mach_number" : 0
        },
        "geometry" : {
            "file" : "studies/filament_studies/Grid_convergence/meshes/conventional_NACA_7.stl",
            "spanwise_axis" : "+y",
            "reference" : {
                "area" : 5.00000000000000E+001
            },
            "wake_model" : {
                "wake_present" : true,
                "append_wake" : true,
                "trefftz_distance" : 600,
                "wake_type" : "panels"
            }
        },
        "solver" : {
            "ormulation" : "neumann-mass-flux",
            "formulation" : "dirichlet-morino",
            "matrix_solver" : "GMRES",
            "write_A_and_b" : false
        },
        "post_processing" : {
            "pressure_rules" : {
                "ncompressible" : true
            }
        },
        "output" : {
            "body_file" : "studies/filament_studies/Grid_convergence/results/conventional_NACA7.vtk",
            "wake_file" : "studies/filament_studies/Grid_convergence/results/conventional_NACA7_wake.vtk",
            "report_file" : "studies/filament_studies/Grid_convergence/reports/conventional_NACA7.json"
        }
    },
    "total_runtime" : 2.64218000000000E+002
}
