{
    "flow": {
        "freestream_velocity": [
            1.0,
            0.0,
            0.1
        ],
        "freestream_mach_number": 2.0
    },
    "geometry": {
        "file": "studies/adjoint_studies/central_diff_norm_cp_offset/meshes/test_11.stl",
        "wake_model": {
            "wake_present": true,
            "wake_appended": true
        },
        "adjoint_sensitivities": {
            "calc_adjoint": true,
            "robust_cp_dir": true
        },
        "perturbation": {
            "perturb_point": false,
            "point_index": 0,
            "xyz_index": 0,
            "step": -1e-06
        }
    },
    "solver": {
        "formulation": "dirichlet-source-free",
        "control_point_offset": 0.0001,
        "matrix_solver": "GMRES"
    },
    "post_processing": {
        "pressure_rules": {
            "isentropic": true
        }
    },
    "output": {
        "verbose": false,
        "report_file": "studies/adjoint_studies/central_diff_norm_cp_offset/reports/1.json",
        "body_file": "studies/adjoint_studies/central_diff_norm_cp_offset/vtk_files/adjoint_test_11_cp_1.00e-04.vtk"
    }
}