{
    "info" : {
        "generated_by" : "MachLine (c) 2023 USU Aerolab",
        "executed" : "Fri Oct 13 01:39:00 2023"
    },
    "mesh_info" : {
        "N_body_panels" : 22016,
        "N_body_vertices" : 11214,
        "N_wake_panels" : 408,
        "N_wake_filaments" : 0,
        "average_characteristic_length" : 9.12443047595278E-002,
        "max_flow_turning_angle" : 1.72084793182362E+002
    },
    "solver_results" : {
        "solver_status_code" : 0,
        "system_dimension" : 11214,
        "timing" : {
            "system_sorting" : 1.88000000000000E-005,
            "preconditioner" : 1.76429985560000E+003,
            "matrix_solver" : 1.08929498600000E+002
        },
        "iterations" : 999,
        "residual" : {
            "max" : 3.02008178050871E-001,
            "norm" : 5.46331058622729E+000
        }
    },
    "pressure_calculations" : {
        "incompressible_rule" : {
            "max" : 9.64697416143553E-001,
            "min" : -3.14375634543129E+000
        }
    },
    "total_forces" : {
        "Cx" : -6.42406261753105E-003,
        "Cy" : 1.25188650200946E-010,
        "Cz" : 1.07637647288317E-001
    },
    "total_moments" : {
        "CMx" : -3.62951774149790E-008,
        "CMy" : 1.00093860127028E+001,
        "CMz" : 1.79340706624642E-007
    },
    "input" : {
        "flow" : {
            "freestream_velocity" : [
                    9.96194698091746E-001,
                    0.00000000000000E+000,
                    8.71557427476582E-002
                ],
            "freestream_mach_number" : [
                    2.50000000000000E-001,
                    1.70000000000000E+000
                ]
        },
        "geometry" : {
            "file" : "studies/filament_studies/Grid_convergence/meshes/bi_plane_grid_convergence_12.stl",
            "spanwise_axis" : "+y",
            "reference" : {
                "area" : 5.00000000000000E+001
            },
            "wake_model" : {
                "wake_present" : true,
                "append_wake" : true,
                "trefftz_distance" : 60,
                "wake_type" : [
                        "panels",
                        "filaments"
                    ]
            }
        },
        "solver" : {
            "formulation" : "neumann-mass-flux",
            "ormulation" : "dirichlet-morino",
            "matrix_solver" : "GMRES",
            "write_A_and_b" : false
        },
        "post_processing" : {
            "pressure_rules" : {
                "ncompressible" : true
            }
        },
        "output" : {
            "body_file" : "studies/filament_studies/Grid_convergence/results/12.vtk",
            "wake_file" : "studies/filament_studies/Grid_convergence/results/12_wake.vtk",
            "report_file" : "studies/filament_studies/Grid_convergence/reports/12.json"
        }
    },
    "total_runtime" : 2.50425000000000E+003
}
