{
    "info" : {
        "generated_by" : "MachLine (c) 2023 USU Aerolab",
        "executed" : "Fri Jul 19 09:03:11 2024"
    },
    "mesh_info" : {
        "N_body_panels" : 48,
        "N_body_vertices" : 26,
        "N_wake_panels" : 0,
        "N_wake_filaments" : 0,
        "average_characteristic_length" : 4.76887257362578E-001,
        "max_flow_turning_angle" : 9.00000000000000E+001
    },
    "solver_results" : {
        "solver_status_code" : 0,
        "system_dimension" : 26,
        "timing" : {
            "system_sorting" : 2.20000000000000E-006,
            "preconditioner" : 8.80000000000000E-006,
            "matrix_solver" : 1.85000000000000E-005
        },
        "iterations" : 8,
        "residual" : {
            "max" : 3.33066907387547E-015,
            "norm" : 1.17881216201863E-014
        }
    },
    "pressure_calculations" : {
        "incompressible_rule" : {
            "max" : 7.23154980942327E-001,
            "min" : -6.52444857661567E-001
        }
    },
    "total_forces" : {
        "Cx" : -7.30911005008789E-003,
        "Cy" : -1.76970785469299E-005,
        "Cz" : -1.94783516201768E-002
    },
    "total_moments" : {
        "CMx" : 5.97999794873377E-008,
        "CMy" : 1.55327244524077E-002,
        "CMz" : -2.27931854196797E-005
    },
    "input" : {
        "flow" : {
            "freestream_velocity" : [
                    1.00000000000000E+000,
                    0.00000000000000E+000,
                    0.00000000000000E+000
                ]
        },
        "geometry" : {
            "file" : "studies/adjoint_studies/central_diff_norm_cp_offset/meshes/sphere_coarse2.stl",
            "wake_model" : {
                "wake_present" : false
            },
            "adjoint_sensitivities" : {
                "calc_adjoint" : false
            },
            "perturbation" : {
                "perturb_point" : true,
                "point_index" : 26,
                "xyz_index" : 3,
                "step" : -1.00000000000000E-001
            }
        },
        "solver" : {
            "formulation" : "dirichlet-source-free",
            "control_point_offset" : 1.59955802861467E-012,
            "matrix_solver" : "GMRES"
        },
        "post_processing" : {
            "pressure_rules" : {
                "incompressible" : true
            }
        },
        "output" : {
            "report_file" : "studies/adjoint_studies/central_diff_norm_cp_offset/reports/cp_offset_1_5995580286146712e-12_dirichlet_source_free.json"
        }
    },
    "total_runtime" : 1.50000000000000E-002
}
