{
    "info" : {
        "generated_by" : "MachLine (c) 2023 USU Aerolab",
        "executed" : "Wed Jul 17 16:10:56 2024"
    },
    "mesh_info" : {
        "N_body_panels" : 48,
        "N_body_vertices" : 26,
        "N_wake_panels" : 0,
        "N_wake_filaments" : 0,
        "average_characteristic_length" : 4.76931461379173E-001,
        "max_flow_turning_angle" : 9.00000000000000E+001
    },
    "solver_results" : {
        "solver_status_code" : 0,
        "system_dimension" : 26,
        "timing" : {
            "system_sorting" : 2.10000000000000E-006,
            "preconditioner" : 3.90000000000000E-006,
            "matrix_solver" : 2.28000000000000E-005
        },
        "iterations" : 6,
        "residual" : {
            "max" : 1.15463194561016E-013,
            "norm" : 2.44508004943820E-013
        }
    },
    "pressure_calculations" : {
        "incompressible_rule" : {
            "max" : 6.43011090391386E-001,
            "min" : -6.53211023234054E-001
        }
    },
    "total_forces" : {
        "Cx" : -9.49342780567908E-007,
        "Cy" : 1.55555062106294E-006,
        "Cz" : 1.14109915154426E-006
    },
    "total_moments" : {
        "CMx" : 2.17283522771505E-010,
        "CMy" : -4.28711821458955E-006,
        "CMz" : 5.14087090018600E-006
    },
    "input" : {
        "flow" : {
            "freestream_velocity" : [
                    1.00000000000000E+000,
                    0.00000000000000E+000,
                    0.00000000000000E+000
                ]
        },
        "geometry" : {
            "file" : "studies/adjoint_studies/central_diff_norm_cp_offset/meshes/sphere_coarse2.stl",
            "wake_model" : {
                "wake_present" : false
            },
            "adjoint_sensitivities" : {
                "calc_adjoint" : false
            },
            "perturbation" : {
                "perturb_point" : true,
                "point_index" : 25,
                "xyz_index" : 1,
                "step" : 1.00000000000000E-005
            }
        },
        "solver" : {
            "formulation" : "dirichlet-source-free",
            "control_point_offset" : 1.18032063565173E-003,
            "matrix_solver" : "GMRES"
        },
        "post_processing" : {
            "pressure_rules" : {
                "incompressible" : true
            }
        },
        "output" : {
            "report_file" : "studies/adjoint_studies/central_diff_norm_cp_offset/reports/cp_offset_0_0011803206356517323_dirichlet_source_free.json"
        }
    },
    "total_runtime" : 1.60000000000000E-002
}
